catalyst_codestyle-21.9.2.data/scripts/catalyst-check-codestyle
catalyst_codestyle-21.9.2.data/scripts/catalyst-make-codestyle
codestyle/__init__.py
codestyle/_flake8.py
codestyle/_isort.py
catalyst_codestyle-21.9.2.dist-info/LICENSE
catalyst_codestyle-21.9.2.dist-info/METADATA
catalyst_codestyle-21.9.2.dist-info/WHEEL
catalyst_codestyle-21.9.2.dist-info/entry_points.txt
catalyst_codestyle-21.9.2.dist-info/top_level.txt
catalyst_codestyle-21.9.2.dist-info/RECORD
