Metadata-Version: 2.1
Name: catalyst-codestyle
Version: 21.9.2
Summary: Catalyst.Codestyle
Home-page: https://github.com/catalyst-team/codestyle
Author: Sergey Kolesnikov
Author-email: scitator@gmail.com
License: Apache License 2.0
Download-URL: https://github.com/catalyst-team/codestyle
Project-URL: Bug Tracker, https://github.com/catalyst-team/codestyle/issues
Project-URL: Documentation, https://catalyst-team.github.io/catalyst
Project-URL: Source Code, https://github.com/catalyst-team/codestyle
Platform: UNKNOWN
Classifier: Environment :: Console
Classifier: Natural Language :: English
Classifier: Development Status :: 4 - Beta
Classifier: Operating System :: OS Independent
Classifier: License :: OSI Approved :: Apache Software License
Classifier: Intended Audience :: Developers
Classifier: Intended Audience :: Science/Research
Classifier: Programming Language :: Python
Classifier: Programming Language :: Python :: 3.6
Classifier: Programming Language :: Python :: 3.7
Classifier: Programming Language :: Python :: 3.8
Classifier: Programming Language :: Python :: 3.9
Classifier: Programming Language :: Python :: Implementation :: CPython
Requires-Python: >=3.6.0
License-File: LICENSE
Requires-Dist: black (>=19.10b0)
Requires-Dist: flake8 (<4.0,>=3.7)
Requires-Dist: flake8-blind-except (<0.2,>=0.1.1)
Requires-Dist: flake8-broken-line (<0.4,>=0.3)
Requires-Dist: flake8-bugbear (<22.0,>=20.1)
Requires-Dist: flake8-comprehensions (<4.0,>=3.1)
Requires-Dist: flake8-debugger (<5.0,>=4.0)
Requires-Dist: flake8-docstrings (<2.0,>=1.4)
Requires-Dist: flake8-quotes (<4.0,>=3.0)
Requires-Dist: flake8-rst-docstrings (<0.3.0,>=0.2.3)
Requires-Dist: flake8-string-format (<0.4,>=0.3)
Requires-Dist: pep8-naming (<0.13,>=0.11)
Requires-Dist: darglint (<2.0,>=1.5)
Requires-Dist: isort (<6.0,>=5.0)
Requires-Dist: nitpick (<0.28,>=0.27)
